README.md
setup.py
Smarties/SmartiesAPI.py
Smarties/__init__.py
Smarties/rake.py
Smarties.egg-info/PKG-INFO
Smarties.egg-info/SOURCES.txt
Smarties.egg-info/dependency_links.txt
Smarties.egg-info/not-zip-safe
Smarties.egg-info/requires.txt
Smarties.egg-info/top_level.txt