Metadata-Version: 1.0
Name: Smarties
Version: 0.11
Summary: A Smart AI Text Learner and Classifier
Home-page: https://github.com/anisayari/Smarties
Author: Anis Ayari
Author-email: anis.ayari.pro@gmail.com
License: GPL3
Platform: UNKNOWN
